README.md
setup.py
biscuit/__init__.py
biscuit_cookies.egg-info/PKG-INFO
biscuit_cookies.egg-info/SOURCES.txt
biscuit_cookies.egg-info/dependency_links.txt
biscuit_cookies.egg-info/requires.txt
biscuit_cookies.egg-info/top_level.txt